meowmx/__init__.py
meowmx/aggregates.py
meowmx/backoff.py
meowmx/client.py
meowmx/py.typed
meowmx/aggregates/__init__.py
meowmx/aggregates/aggregate.py
meowmx/aggregates/buffer.py
meowmx/aggregates/pending.py
meowmx/common/__init__.py
meowmx/common/client.py
meowmx/common/types.py
meowmx/esp/__init__.py
meowmx/esp/esp.py
meowmx/esp/migrations.py
meowmx/sqlalchemy/__init__.py
meowmx/sqlalchemy/client.py
meowmx/sqlalchemy/locked.py
meowmx/sqlalchemy/tables.py
meowmx/workers/__init__.py
meowmx/workers/tables.py
meowmx/workers/worker.py
meowmx-0.2.2.dist-info/METADATA
meowmx-0.2.2.dist-info/WHEEL
meowmx-0.2.2.dist-info/licenses/LICENSE
meowmx-0.2.2.dist-info/RECORD
