Metadata-Version: 2.4
Name: meowmx
Version: 0.2.2
Summary: Managed Event Orchestration With Multiple eXecutors
Author: Tim Simpson
License-Expression: Apache-2.0
License-File: LICENSE
Classifier: Development Status :: 3 - Alpha
Classifier: Intended Audience :: Developers
Classifier: Programming Language :: Python :: 3.13
Requires-Python: >=3.11
Requires-Dist: sqlalchemy>=2.0.43
